socketclusterclient/Emitter.py
socketclusterclient/Parser.py
socketclusterclient/Socketcluster.py
socketclusterclient/__init__.py
socketclusterclient-1.3.6.dist-info/LICENSE.txt
socketclusterclient-1.3.6.dist-info/METADATA
socketclusterclient-1.3.6.dist-info/WHEEL
socketclusterclient-1.3.6.dist-info/top_level.txt
socketclusterclient-1.3.6.dist-info/RECORD
