Metadata-Version: 2.1
Name: socketclusterclient
Version: 1.3.6
Summary: Client library for socketcluster framework in nodejs
Home-page: https://github.com/sacOO7/socketcluster-client-python
Author: Sachin Shinde
Author-email: sachinshinde7676@gmail.com
License: MIT
Download-URL: https://github.com/sacOO7/socketcluster-client-python/tarball/v1.3.6
Keywords: websocket,socketcluster,nodejs,client,socketclusterclient
Platform: UNKNOWN
Classifier: Programming Language :: Python :: 2
Classifier: Programming Language :: Python :: 3
Classifier: License :: OSI Approved :: MIT License
Classifier: Operating System :: OS Independent
Requires-Python: >=2.7
Requires-Dist: websocket-client (<=0.48)
